LICENSE
MANIFEST.in
README.md
requirements.txt
setup.py
tord/__init__.py
tord/tord.py
tord.egg-info/PKG-INFO
tord.egg-info/SOURCES.txt
tord.egg-info/dependency_links.txt
tord.egg-info/requires.txt
tord.egg-info/top_level.txt
tord/static/tord/tord.js